vedro_git_changed/__init__.py
vedro_git_changed/_git_changed_plugin.py
vedro_git_changed/_git_repo.py
vedro_git_changed-0.2.0.dist-info/LICENSE
vedro_git_changed-0.2.0.dist-info/METADATA
vedro_git_changed-0.2.0.dist-info/WHEEL
vedro_git_changed-0.2.0.dist-info/top_level.txt
vedro_git_changed-0.2.0.dist-info/RECORD
