Metadata-Version: 2.1
Name: vedro-git-changed
Version: 0.2.0
Summary: Vedro plugin that runs test scenarios which have changed relative to the specified git branch
Home-page: https://github.com/vedro-universe/vedro-git-changed
Author: Nikita Tsvetkov
Author-email: tsv1@fastmail.com
License: Apache-2.0
Project-URL: Docs, https://github.com/vedro-universe/vedro-git-changed
Project-URL: GitHub, https://github.com/vedro-universe/vedro-git-changed
Classifier: License :: OSI Approved :: Apache Software License
Classifier: Programming Language :: Python :: 3.8
Classifier: Programming Language :: Python :: 3.9
Classifier: Programming Language :: Python :: 3.10
Classifier: Programming Language :: Python :: 3.11
Classifier: Programming Language :: Python :: 3.12
Classifier: Typing :: Typed
Requires-Python: >=3.8
License-File: LICENSE
Requires-Dist: vedro <2.0,>=1.12
Requires-Dist: GitPython <4.0,>=3.1
